Workbook

Sheet Read me
A1: ArabicaAI | Intake cost sensitivity
A3: Decision use | B3: Budget a small synthetic-data demo; validate V1 outcomes before claiming savings or production capacity.
A5: Observed demand | B5: 4,118 V1 complaints in 2025 (complete calendar year); not logged application starts or production traffic.
A6: Today | B6: The demo has no model calls and no deployed cloud service. Model and cloud costs are proposed scenarios.
A7: Scenarios | B7: 11.3/day V1 complaint proxy, then 100, 900, and 9,000/day stress assumptions.
A8: Interpretation | B8: 900/day is an all-contact stress case, not V1 demand. Constant VM pricing does not establish capacity.
A9: Missing outcome | B9: Safe accepted intake / all eligible starts and safe automated resolution are unmeasured.
A10: Important limit | B10: Lightsail VM self-hosts PostgreSQL in the $24 scenario; managed DB is a separate $30 add-on.
A11: Editing | B11: Change pale-yellow values on Inputs. Blue-green cells on Scenarios recalculate in Excel/LibreOffice.
A12: Cloudflare candidate | B12: Worker + D1 may have $0 fixed cloud cost inside Free limits; a code migration and CPU/D1 checks are required. See its separate sheet.
A13: Not in estimate | B13: Taxes, exchange rates, domain, paid logs, egress overages, S3 transfer, model tools/audio, labor, support, HA, security operations.
A15: Reviewed | B15: 2026-09-29; prices should be rechecked before spending. No credits assumed.

Sheet Inputs
A1: Editable inputs | yellow = change with evidence
A3: Parameter | B3: Value | C3: Unit | D3: Definition or source | E3: Evidence status
A5: V1 complaints, complete 2025 | B5: 4118 | C5: complaints/year | D5: Silver aggregate: Cargo no reconocido by creation_date | E5: observed synthetic
A6: Calendar days in 2025 | B6: 365 | C6: days | D6: Calendar fact | E6: fact
A7: Modeled days per month | B7: 30 | C7: days | D7: Comparable 30-day month | E7: assumption
A8: Current HTTP requests per episode | B8: 3 | C8: requests | D8: POST session, GET charges, POST case; agent reads excluded | E8: code-derived
A9: Planned HTTP requests per episode | B9: 10 | C9: requests | D9: Future AI flow; measure from application traces | E9: assumption
A10: Peak-hour fraction | B10: 0.1 | C10: share of day's requests | D10: 10% of daily traffic in busiest hour | E10: assumption
A11: Within-hour burst multiplier | B11: 1 | C11: factor | D11: Set >1 to stress minute-level clustering | E11: assumption
A12: Mean request service time | B12: 2 | C12: seconds | D12: Not measured; not a p95 or capacity test | E12: assumption
A13: AI input tokens per episode | B13: 12000 | C13: tokens | D13: Total across model calls; no AI is running today | E13: assumption
A14: AI output tokens per episode | B14: 2000 | C14: tokens | D14: Total across model calls, including billed reasoning output | E14: assumption
A15: Model input rate | B15: 0.2 | C15: USD / 1M tokens | D15: OpenAI GPT-5.6 Luna standard text input | E15: official price
A16: Model output rate | B16: 1.2 | C16: USD / 1M tokens | D16: OpenAI GPT-5.6 Luna standard text output | E16: official price
... A29: Confirmed model API monthly credit | B29: 0 | C29: USD/month | D29: Only if verified with model provider | E29: unconfirmed
A30: Safe accepted-intake rate | C30: share of eligible starts | D30: Blank until start-to-acceptance events exist | E30: not measured
A31: Safe automated-resolution rate | C31: share of eligible starts | D31: Blank; a handoff does not count as resolution | E31: not measured
A32: Agent minutes saved per accepted case | C32: minutes | D32: Blank: no causal comparison or time study | E32: not measured
A33: Loaded agent cost per minute | C33: USD/minute | D33: Blank: no approved labor-cost assumption | E33: not measured
A34: Illustrative model | B34: gpt-5.6-luna | C34: model | D34: Not implemented or selected for V1 | E34: illustrative
A35: Eligible starts per complaint proxy | B35: 1 | C35: starts/complaint | D35: Only for demand illustration; complaint != observed app start | E35: assumption

Sheet Scenarios
A1: Volume, token and infrastructure sensitivity
A2: All totals USD/month, before taxes. Planned AI assumes GPT-5.6 Luna standard text; current demo uses no AI.
A4: Scenario | B4: Episodes/day | C4: Episodes/month | D4: Current HTTP req/month | E4: Planned HTTP req/month | F4: Peak planned req/hour | G4: Peak req/s | H4: Mean in-flight req | I4: AI USD/episode | J4: AI USD/month | K4: Render fixed USD/month | L4: AWS single VM fixed | M4: AWS + managed DB fixed | N4: Render + AI USD/month | O4: AWS single VM + AI | P4: AWS managed DB + AI | Q4: Cost / safe auto resolution | R4: Render + AI / attempt | S4: Render without AI / attempt
A5: 2025 V1 complaint proxy | B5: =Inputs!B5/Inputs!B6*Inputs!B35 -> 11.282192 | C5: =B5*Inputs!B7 -> 338.46575 | D5: =C5*Inputs!B8 -> 1015.3973 | E5: =C5*Inputs!B9 -> 3384.6575 | F5: =B5*Inputs!B9*Inputs!B10*Inputs!B11 -> 11.282192 | G5: =F5/3600 -> 0.0031339422 | H5: =G5*Inputs!B12 -> 0.0062678843 | I5: =(Inputs!B13*Inputs!B15+Inputs!B14*Inputs!B16)/1000000 -> 0.0048 | J5: =MAX(0,C5*I5-Inputs!B29) -> 1.6246356 | K5: =MAX(0,Inputs!B17+Inputs!B18+Inputs!B19*Inputs!B20+Inputs!B26-Inputs!B28) -> 13.3 | L5: =MAX(0,Inputs!B21+Inputs!B22*Inputs!B23+Inputs!B24+Inputs!B26-Inputs!B27) -> 26 | M5: =L5+Inputs!B25 -> 56 | N5: =J5+K5 -> 14.924636 | O5: =J5+L5 -> 27.624636 | P5: =J5+M5 -> 57.624636 | Q5: =IF(OR(NOT(ISNUMBER(Inputs!B31)),Inputs!B31<=0),"not defined",N5/(C5*Inputs!B31)) -> not defined | R5: =IF(C5>0,N5/C5,"not defined") -> 0.044094965 | S5: =IF(C5>0,K5/C5,"not defined") -> 0.039294965
A6: 100/day test | B6: 100 | C6: =B6*Inputs!B7 -> 3000 | D6: =C6*Inputs!B8 -> 9000 | E6: =C6*Inputs!B9 -> 30000 | F6: =B6*Inputs!B9*Inputs!B10*Inputs!B11 -> 100 | G6: =F6/3600 -> 0.027777778 | H6: =G6*Inputs!B12 -> 0.055555556 | I6: =(Inputs!B13*Inputs!B15+Inputs!B14*Inputs!B16)/1000000 -> 0.0048 | J6: =MAX(0,C6*I6-Inputs!B29) -> 14.4 | K6: =MAX(0,Inputs!B17+Inputs!B18+Inputs!B19*Inputs!B20+Inputs!B26-Inputs!B28) -> 13.3 | L6: =MAX(0,Inputs!B21+Inputs!B22*Inputs!B23+Inputs!B24+Inputs!B26-Inputs!B27) -> 26 | M6: =L6+Inputs!B25 -> 56 | N6: =J6+K6 -> 27.7 | O6: =J6+L6 -> 40.4 | P6: =J6+M6 -> 70.4 | Q6: =IF(OR(NOT(ISNUMBER(Inputs!B31)),Inputs!B31<=0),"not defined",N6/(C6*Inputs!B31)) -> not defined | R6: =IF(C6>0,N6/C6,"not defined") -> 0.0092333333 | S6: =IF(C6>0,K6/C6,"not defined") -> 0.0044333333
A7: 900/day all-contact stress | B7: 900 | C7: =B7*Inputs!B7 -> 27000 | D7: =C7*Inputs!B8 -> 81000 | E7: =C7*Inputs!B9 -> 270000 | F7: =B7*Inputs!B9*Inputs!B10*Inputs!B11 -> 900 | G7: =F7/3600 -> 0.25 | H7: =G7*Inputs!B12 -> 0.5 | I7: =(Inputs!B13*Inputs!B15+Inputs!B14*Inputs!B16)/1000000 -> 0.0048 | J7: =MAX(0,C7*I7-Inputs!B29) -> 129.6 | K7: =MAX(0,Inputs!B17+Inputs!B18+Inputs!B19*Inputs!B20+Inputs!B26-Inputs!B28) -> 13.3 | L7: =MAX(0,Inputs!B21+Inputs!B22*Inputs!B23+Inputs!B24+Inputs!B26-Inputs!B27) -> 26 | M7: =L7+Inputs!B25 -> 56 | N7: =J7+K7 -> 142.9 | O7: =J7+L7 -> 155.6 | P7: =J7+M7 -> 185.6 | Q7: =IF(OR(NOT(ISNUMBER(Inputs!B31)),Inputs!B31<=0),"not defined",N7/(C7*Inputs!B31)) -> not defined | R7: =IF(C7>0,N7/C7,"not defined") -> 0.0052925926 | S7: =IF(C7>0,K7/C7,"not defined") -> 0.00049259259
A8: 9,000/day stress | B8: 9000 | C8: =B8*Inputs!B7 -> 270000 | D8: =C8*Inputs!B8 -> 810000 | E8: =C8*Inputs!B9 -> 2700000 | F8: =B8*Inputs!B9*Inputs!B10*Inputs!B11 -> 9000 | G8: =F8/3600 -> 2.5 | H8: =G8*Inputs!B12 -> 5 | I8: =(Inputs!B13*Inputs!B15+Inputs!B14*Inputs!B16)/1000000 -> 0.0048 | J8: =MAX(0,C8*I8-Inputs!B29) -> 1296 | K8: =MAX(0,Inputs!B17+Inputs!B18+Inputs!B19*Inputs!B20+Inputs!B26-Inputs!B28) -> 13.3 | L8: =MAX(0,Inputs!B21+Inputs!B22*Inputs!B23+Inputs!B24+Inputs!B26-Inputs!B27) -> 26 | M8: =L8+Inputs!B25 -> 56 | N8: =J8+K8 -> 1309.3 | O8: =J8+L8 -> 1322 | P8: =J8+M8 -> 1352 | Q8: =IF(OR(NOT(ISNUMBER(Inputs!B31)),Inputs!B31<=0),"not defined",N8/(C8*Inputs!B31)) -> not defined | R8: =IF(C8>0,N8/C8,"not defined") -> 0.0048492593 | S8: =IF(C8>0,K8/C8,"not defined") -> 4.9259259e-05
A10: Current demo cloud spend | B10: Not deployed: $0 actual cloud bill. Render fixed cost is hypothetical if deployed.
A11: Capacity warning | B11: Peak req/s and in-flight values are arithmetic from assumptions, not a benchmark or a latency guarantee.
A12: Success warning | B12: Cost per safe automated resolution is not defined until numerator and eligible-start denominator are observed.

Sheet Evidence and prices
A1: Sources, scope and pricing basis
A3: Item | B3: Evidence | C3: Source URL or repo path | D3: Interpretation
A4: V1 demand | B4: 4,118 complaints in 2025; 12,297 all dates; 6,192 via Call Center all dates | C4: data_foundation/reports/aggregates.json | D4: Synthetic complaints, not app starts or forecast
A5: Actual application | B5: FastAPI intake; 3 customer HTTP calls in normal path; no AI SDK or model call | C5: demo_api.py; demo-ui/src/app/app.ts | D5: No measured tokens, p95 or production throughput
A6: Hackathon metric | B6: Cost per attempt and successful automated resolution, with denominator | C6: Docs/FACTORED_HACKATHON_2026.md | D6: Handoff is not automated resolution
A7: OpenAI model | B7: GPT-5.6 Luna standard: $0.20 input, $1.20 output per million text tokens | C7: https://developers.openai.com/api/docs/models/gpt-5.6-luna | D7: Illustrative provider/model; no cache, tool, audio or batch discount
A8: AWS Lightsail | B8: $24/mo IPv4 Linux VM 4GB; $0.05/GB-month snapshots; $1/mo 5GB object bundle; $30/mo 2GB encrypted managed DB | C8: https://aws.amazon.com/lightsail/pricing/ | D8: VM alone means self-managed PostgreSQL; capacity untested
A9: Render | B9: $7/mo web, $6/mo Postgres, $0.30/GB-month allocated Postgres storage | C9: https://render.com/pricing | D9: Paid proposed deployment; job, egress, taxes extra
A10: AWS credits | B10: Up to $200 for eligible new accounts; workbook assumes zero | C10: https://aws.amazon.com/free/ | D10: AWS credits cannot reduce separate OpenAI bill
A11: Official AWS calculator | B11: Use for region and service-specific quote before purchase | C11: https://calculator.aws/ | D11: This workbook is not a calculator export
A12: Cloudflare Workers Free | B12: 100,000 requests/day, 10 ms CPU/request | C12: https://developers.cloudflare.com/workers/platform/pricing/ | D12: Conditional free candidate; this report has no measured CPU usage
A13: Cloudflare D1 Free | B13: 5M rows read/day, 100k rows written/day, 500 MB per database | C13: https://developers.cloudflare.com/d1/platform/limits/ | D13: No measured D1 row scans or storage forecast

Sheet Cloudflare candidate
A1: Cloudflare Worker + D1 | conditional Free plan
A2: A connected GitHub repo does not migrate the current PostgreSQL demo. The Worker variant must pass live CPU and D1 checks.
A4: Scenario | B4: Episodes/day | C4: Planned Worker req/day | D4: Free req/day cap | E4: Request headroom | F4: Request-cap check | G4: Illustrative AI USD/month
A5: =Scenarios!A5 -> 2025 V1 complaint proxy | B5: =Scenarios!B5 -> 11.282192 | C5: =B5*Inputs!B9 -> 112.82192 | D5: 100000 | E5: =D5-C5 -> 99887.178 | F5: =IF(C5<=D5,"under request cap","over request cap") -> under request cap | G5: =Scenarios!J5 -> 1.6246356
A6: =Scenarios!A6 -> 100/day test | B6: =Scenarios!B6 -> 100 | C6: =B6*Inputs!B9 -> 1000 | D6: 100000 | E6: =D6-C6 -> 99000 | F6: =IF(C6<=D6,"under request cap","over request cap") -> under request cap | G6: =Scenarios!J6 -> 14.4
A7: =Scenarios!A7 -> 900/day all-contact stress | B7: =Scenarios!B7 -> 900 | C7: =B7*Inputs!B9 -> 9000 | D7: 100000 | E7: =D7-C7 -> 91000 | F7: =IF(C7<=D7,"under request cap","over request cap") -> under request cap | G7: =Scenarios!J7 -> 129.6
A8: =Scenarios!A8 -> 9,000/day stress | B8: =Scenarios!B8 -> 9000 | C8: =B8*Inputs!B9 -> 90000 | D8: 100000 | E8: =D8-C8 -> 10000 | F8: =IF(C8<=D8,"under request cap","over request cap") -> under request cap | G8: =Scenarios!J8 -> 1296
A10: Potential fixed hosting | B10: $0 only while Worker and D1 stay inside Free quotas; not a capacity promise.
A11: Still unmeasured | B11: CPU ms/request (Free: 10 ms); D1 rows read/write, DB size, retries, static requests, peak traffic.
A12: Model charges | B12: AI usage in column G is hypothetical and billed separately from Cloudflare. Current demo uses no model.
A13: Readiness | B13: The 9,000/day scenario has only 10,000 requests/day headroom under the assumed 10 calls/episode.
